minecraft_data/__init__.py
minecraft_data/tools.py
minecraft_data/data/README.md
minecraft_data/data/data/dataPaths.json
minecraft_data/data/data/bedrock/0.14/blocks.json
minecraft_data/data/data/bedrock/0.14/items.json
minecraft_data/data/data/bedrock/0.14/protocol.json
minecraft_data/data/data/bedrock/0.14/version.json
minecraft_data/data/data/bedrock/0.15/blocks.json
minecraft_data/data/data/bedrock/0.15/items.json
minecraft_data/data/data/bedrock/0.15/protocol.json
minecraft_data/data/data/bedrock/0.15/version.json
minecraft_data/data/data/bedrock/1.0/blocks.json
minecraft_data/data/data/bedrock/1.0/items.json
minecraft_data/data/data/bedrock/1.0/version.json
minecraft_data/data/data/bedrock/1.16.201/attributes.json
minecraft_data/data/data/bedrock/1.16.201/enchantments.json
minecraft_data/data/data/bedrock/1.16.201/language.json
minecraft_data/data/data/bedrock/1.16.201/proto.yml
minecraft_data/data/data/bedrock/1.16.201/protocol.json
minecraft_data/data/data/bedrock/1.16.201/steve.json
minecraft_data/data/data/bedrock/1.16.201/types.yml
minecraft_data/data/data/bedrock/1.16.201/version.json
minecraft_data/data/data/bedrock/1.16.201/windows.json
minecraft_data/data/data/bedrock/1.16.210/language.json
minecraft_data/data/data/bedrock/1.16.210/proto.yml
minecraft_data/data/data/bedrock/1.16.210/protocol.json
minecraft_data/data/data/bedrock/1.16.210/types.yml
minecraft_data/data/data/bedrock/1.16.210/version.json
minecraft_data/data/data/bedrock/1.16.220/blockStates.json
minecraft_data/data/data/bedrock/1.16.220/blocks.json
minecraft_data/data/data/bedrock/1.16.220/language.json
minecraft_data/data/data/bedrock/1.16.220/proto.yml
minecraft_data/data/data/bedrock/1.16.220/protocol.json
minecraft_data/data/data/bedrock/1.16.220/types.yml
minecraft_data/data/data/bedrock/1.16.220/version.json
minecraft_data/data/data/bedrock/1.17.0/biomes.json
minecraft_data/data/data/bedrock/1.17.0/blockCollisionShapes.json
minecraft_data/data/data/bedrock/1.17.0/blockStates.json
minecraft_data_latest-0.2.dist-info/LICENSE
minecraft_data_latest-0.2.dist-info/METADATA
minecraft_data_latest-0.2.dist-info/WHEEL
minecraft_data_latest-0.2.dist-info/top_level.txt
minecraft_data_latest-0.2.dist-info/RECORD
